rexmv.py
rexmv-0.2.0.dist-info/DESCRIPTION.rst
rexmv-0.2.0.dist-info/METADATA
rexmv-0.2.0.dist-info/RECORD
rexmv-0.2.0.dist-info/WHEEL
rexmv-0.2.0.dist-info/entry_points.txt
rexmv-0.2.0.dist-info/metadata.json
rexmv-0.2.0.dist-info/top_level.txt
