Metadata-Version: 2.0
Name: rexmv
Version: 0.2.0
Summary: Rename file based on regex and string templates
Home-page: UNKNOWN
Author: Dennis Fink
Author-email: dennis.fink@c3l.lu
License: GPLv3+
Platform: UNKNOWN
Classifier: Development Status :: 4 - Beta
Classifier: Intended Audience :: End Users/Desktop
Classifier: Intended Audience :: System Administrators
Classifier: License :: OSI Approved :: GNU General Public License v3 or later (GPLv3+)
Classifier: Programming Language :: Python :: 3.5
Classifier: Topic :: Utilities
Requires-Dist: click
